<manifest alg="2" build="704" opt="false" iceEnabled="true">
  <folder name="css">
    <file name="site_global.css" crc="3837790900"/>
    <file name="master_a-p_gina-maestra.css" crc="4290081520" ref="index"/>
    <file name="index.css" crc="3929848164" ref="index"/>
  </folder>
  <folder name="assets">
    <folder name="flash1">
      <folder name="edge_includes">
        <file name="edge.1.5.0.min.js" crc="278316596" mt="1384282490000"/>
        <file name="jquery-1.7.1.min.js" crc="111770969" mt="1384282490000"/>
      </folder>
      <folder name="images">
        <file name="d02_10.png" crc="522722255" mt="1384282490000"/>
        <file name="d02_19.png" crc="3848153362" mt="1384282490000"/>
        <file name="d02_20_05.png" crc="161951272" mt="1384282490000"/>
        <file name="o_01.png" crc="48659378" mt="1384282490000"/>
        <file name="o_02.png" crc="467774856" mt="1384282490000"/>
        <file name="o_03.png" crc="77568766" mt="1384282490000"/>
        <file name="o_04.png" crc="4200967059" mt="1384282490000"/>
        <file name="o_05.png" crc="213645182" mt="1384282490000"/>
        <file name="o_06.png" crc="277133418" mt="1384282490000"/>
        <file name="Poster.png" crc="3839333489" mt="1384282490000"/>
      </folder>
      <file name="flash1_edge.js" crc="3761302132" mt="1384282490000"/>
      <file name="flash1_edgeActions.js" crc="70091257" mt="1384282490000"/>
      <file name="flash1_edgePreload.js" crc="316791659" mt="1384282490000"/>
      <file name="flash1.html" crc="304657152" mt="1384282490000"/>
    </folder>
  </folder>
  <folder name="scripts">
    <file name="jquery-1.8.3.min.js" crc="209076791" ref="index"/>
    <file name="museutils.js" crc="3992981318" ref="index"/>
    <file name="pie.js" crc="3827607177" ref="index"/>
    <file name="webpro.js" crc="197321703" ref="index"/>
    <file name="musewpslideshow.js" crc="4283859919" ref="index"/>
    <file name="jquery.museoverlay.js" crc="3836522771" ref="index"/>
    <file name="touchswipe.js" crc="4156838003" ref="index"/>
    <file name="jquery.scrolleffects.js" crc="4278609653" ref="index"/>
    <file name="jquery.watch.js" crc="4068933136" ref="index"/>
  </folder>
  <folder name="images">
    <file name="main_03.png" crc="4095170216" ref="index"/>
    <file name="main_05.png" crc="119880170" ref="index"/>
    <file name="main_58.png" crc="190292977" ref="index"/>
    <file name="main_48.png" crc="136078294" ref="index"/>
    <file name="port_03.png" crc="188424681" ref="index"/>
    <file name="port_06.png" crc="4261242394" ref="index"/>
    <file name="port_07.png" crc="3964546110" ref="index"/>
    <file name="v_20.png" crc="418183194" ref="index"/>
    <file name="d01_03.png" crc="4000998712" ref="index"/>
    <file name="u471.png" crc="4122841031" ref="index"/>
    <file name="u471-r.png" crc="4095169132" ref="index"/>
    <file name="d01_07.png" crc="179548230" ref="index"/>
    <file name="d01_09.png" crc="142100944" ref="index"/>
    <file name="d01_11.png" crc="364126160" ref="index"/>
    <file name="d01_12.png" crc="459625029" ref="index"/>
    <file name="d02_18.png" crc="504619061" ref="index"/>
    <file name="d02_17.png" crc="139302114" ref="index"/>
    <file name="d02_13.png" crc="4112902959" ref="index"/>
    <file name="d02_03.png" crc="365564914" ref="index"/>
    <file name="m03.png" crc="25155091" ref="index"/>
    <file name="d04.png" crc="3883356807" ref="index"/>
    <file name="d04_06.png" crc="306553805" ref="index"/>
    <file name="d04_08.png" crc="3800358499" ref="index"/>
    <file name="d04_13.png" crc="461105107" ref="index"/>
    <file name="d04_18.png" crc="382942714" ref="index"/>
    <file name="d04_24.png" crc="3935964756" ref="index"/>
    <file name="d04_26.png" crc="3841428837" ref="index"/>
    <file name="d04_28.png" crc="3969646529" ref="index"/>
    <file name="d04_21.png" crc="305764124" ref="index"/>
    <file name="m05.png" crc="180580511" ref="index"/>
    <file name="d06-u2102-fr.png" crc="303072483" ref="index"/>
    <file name="d06.png" crc="4147220854" ref="index"/>
    <file name="d06_03.png" crc="304127222" ref="index"/>
    <file name="d06_10.png" crc="299589702" ref="index"/>
    <file name="d06_06.png" crc="3857663432" ref="index"/>
    <file name="d06_14.png" crc="431582241" ref="index"/>
    <file name="d06_18.png" crc="3934279110" ref="index"/>
    <file name="d07a_06.png" crc="3855651156" ref="index"/>
    <file name="d07a_13.png" crc="183784141" ref="index"/>
    <file name="d07_03.png" crc="4191301240" ref="index"/>
    <file name="d07_05.png" crc="339333446" ref="index"/>
    <file name="d07_10.png" crc="377227764" ref="index"/>
    <file name="d07a_17.png" crc="4153023969" ref="index"/>
    <file name="d07a_03.png" crc="4101830862" ref="index"/>
    <file name="d07a_09.png" crc="4025788512" ref="index"/>
    <file name="d08.png" crc="4161920902" ref="index"/>
    <file name="d08_03.png" crc="467065842" ref="index"/>
    <file name="d08_06.png" crc="3916098134" ref="index"/>
    <file name="d10_03.png" crc="42636045" ref="index"/>
    <file name="d11_03.png" crc="6089117" ref="index"/>
    <file name="d11_06.png" crc="3835187255" ref="index"/>
    <file name="d11_07.png" crc="4221484895" ref="index"/>
    <file name="d11_10.png" crc="4140490085" ref="index"/>
    <file name="d12_01.png" crc="40253601" ref="index"/>
    <file name="d12_01_03.png" crc="176440687" ref="index"/>
    <file name="d12_03.png" crc="120778487" ref="index"/>
    <file name="d12_04.png" crc="25148565" ref="index"/>
    <file name="u1425.png" crc="316706410" ref="index"/>
    <file name="u1425-r.png" crc="154133172" ref="index"/>
    <file name="d12_09.png" crc="9449800" ref="index"/>
    <file name="u1435.png" crc="3919530987" ref="index"/>
    <file name="u1435-r.png" crc="48019025" ref="index"/>
    <file name="d12_11.png" crc="3778917080" ref="index"/>
    <file name="d12_15.png" crc="4014238776" ref="index"/>
    <file name="d12_16.png" crc="114237750" ref="index"/>
    <file name="u1455.png" crc="3961408797" ref="index"/>
    <file name="u1455-r.png" crc="3793290502" ref="index"/>
    <file name="d12_02_03.png" crc="250983249" ref="index"/>
    <file name="d13_01.png" crc="3762746665" ref="index"/>
    <file name="d13.png" crc="361730118" ref="index"/>
    <file name="d13_02.png" crc="367096229" ref="index"/>
    <file name="d14_01a.png" crc="4016906752" ref="index"/>
    <file name="d15_01.png" crc="4286784153" ref="index"/>
    <file name="d15_03.png" crc="498994100" ref="index"/>
    <file name="d15_04_03.png" crc="3828759176" ref="index"/>
    <file name="d16.png" crc="125461515" ref="index"/>
    <file name="d16_06.png" crc="49499632" ref="index"/>
    <file name="d16_03.png" crc="3905345863" ref="index"/>
    <file name="d17_05.png" crc="4073469978" ref="index"/>
    <file name="d17_09.png" crc="363956275" ref="index"/>
    <file name="d17_03.png" crc="3923815148" ref="index"/>
    <file name="d17_14.png" crc="330151562" ref="index"/>
    <file name="d17_16.png" crc="4062316662" ref="index"/>
    <file name="d17_19.png" crc="480286891" ref="index"/>
    <file name="d18_03.png" crc="3992777156" ref="index"/>
    <file name="d18_032.png" crc="304358011" ref="index"/>
    <file name="d18_06.png" crc="3881736024" ref="index"/>
    <file name="d18_08.png" crc="4092057582" ref="index"/>
    <file name="d18_11.png" crc="457400348" ref="index"/>
    <file name="d18_18.png" crc="3823573677" ref="index"/>
    <file name="d18_05_03.png" crc="3903388577" ref="index"/>
    <file name="d18_03-u1757-fr.png" crc="4258801826" ref="index"/>
    <file name="d18_02-u1758-fr.png" crc="74914978" ref="index"/>
    <file name="d18_01.png" crc="3866379022" ref="index"/>
    <file name="d19.png" crc="424597583" ref="index"/>
    <file name="d19_10.png" crc="5110589" ref="index"/>
    <file name="d19_03.png" crc="214652148" ref="index"/>
    <file name="d19_06.png" crc="3947455964" ref="index"/>
    <file name="v_03.png" crc="4246115942" ref="index"/>
    <file name="v_16.png" crc="56295114" ref="index"/>
    <file name="v_18.png" crc="354827486" ref="index"/>
    <file name="v_08.png" crc="3816359342" ref="index"/>
    <file name="v_12.png" crc="432113072" ref="index"/>
    <file name="v_06.png" crc="3766230513" ref="index"/>
    <file name="v_10.png" crc="3934169682" ref="index"/>
    <file name="d04_01.png" crc="496387976" ref="index"/>
    <file name="line.png" crc="3898389240" ref="index"/>
    <file name="d09_03.png" crc="3785205638" ref="index"/>
    <file name="d09_06.png" crc="464175672" ref="index"/>
    <file name="d09_09.png" crc="199720854" ref="index"/>
    <file name="d09_12.png" crc="819104" ref="index"/>
    <file name="d09_15.png" crc="4261278694" ref="index"/>
    <file name="d20_03.png" crc="64033137" ref="index"/>
    <file name="d20_06.png" crc="4117247449" ref="index"/>
    <file name="d20_09.png" crc="370841997" ref="index"/>
    <file name="fnd25.jpg" crc="3976727235" ref="index"/>
    <file name="d10_03a_03.png" crc="354352333" ref="index"/>
    <file name="d21.png" crc="8715750" ref="index"/>
    <file name="d21_05.png" crc="3882518821" ref="index"/>
    <file name="d21_09.png" crc="4080446058" ref="index"/>
    <file name="d21_03.png" crc="3943402193" ref="index"/>
    <file name="d21_12.png" crc="4070839127" ref="index"/>
    <file name="line001.png" crc="156491350" ref="index"/>
    <file name="line001678x101.png" crc="3999543885" ref="index"/>
    <file name="d22_03.png" crc="3831341784" ref="index"/>
    <file name="d22_03_10.png" crc="67500234" ref="index"/>
    <file name="d22_03_06.png" crc="210390860" ref="index"/>
    <file name="d22_0301.png" crc="3821276789" ref="index"/>
    <file name="d22_03rom.png" crc="482755357" ref="index"/>
  </folder>
  <file name="index.html" crc="411510589" mt="1387220335913"/>
</manifest>